{
  "type": "minecraft:block",
  "pools": [
    {
      "rolls": 1.0,
      "entries": [
        {
          "type": "minecraft:item",
          "name": "hbm_ntm_rebirth:oil_tar_crude",
          "functions": [
            {
              "function": "minecraft:apply_bonus",
              "enchantment": "minecraft:fortune",
              "formula": "minecraft:ore_drops"
            }
          ]
        }
      ],
      "conditions": [
        {
          "condition": "minecraft:survives_explosion"
        }
      ]
    }
  ]
}
