{
  "type": "hbm_ntm_rebirth:assembly_machine",
  "duration": 300,
  "input_fluids": [],
  "input_items": [
    { "count": 4, "ingredient": { "tag": "forge:welded_plates/tungsten" }, "legacy_ore": "plateWeldedTungsten" },
    { "count": 16, "ingredient": { "tag": "forge:cast_plates/any_resistant_alloy" }, "legacy_ore": "plateCastAnyResistantAlloy" },
    { "count": 32, "ingredient": { "tag": "forge:plates/copper" }, "legacy_ore": "plateCopper" },
    { "count": 16, "ingredient": { "tag": "forge:ingots/any_hard_plastic" }, "legacy_ore": "ingotAnyHardPlastic" },
    { "count": 8, "ingredient": { "tag": "forge:dense_wires/bscco" }, "legacy_ore": "wireDenseBSCCO" },
    { "count": 2, "ingredient": { "item": "hbm_ntm_rebirth:circuit_bismoid" }, "legacy_id": "hbm:circuit", "legacy_meta": 12 }
  ],
  "internal_name": "ass.fusionklystron",
  "output_fluids": [],
  "output_items": [
    { "item": "hbm_ntm_rebirth:fusion_klystron" }
  ],
  "pools": [],
  "power": 100,
  "source_order": 179
}
