{
  "parent": "minecraft:recipes/root",
  "criteria": {
    "has_paintable_fluid_duct": {
      "conditions": {
        "items": [
          {
            "items": [
              "hbm:fluid_duct_paintable"
            ]
          }
        ]
      },
      "trigger": "minecraft:inventory_changed"
    },
    "has_the_recipe": {
      "conditions": {
        "recipe": "hbm:fluid_network/fluid_valve"
      },
      "trigger": "minecraft:recipe_unlocked"
    }
  },
  "requirements": [
    [
      "has_paintable_fluid_duct",
      "has_the_recipe"
    ]
  ],
  "rewards": {
    "recipes": [
      "hbm:fluid_network/fluid_valve"
    ]
  },
  "sends_telemetry_event": false
}